coverage_specificity/__init__.py
coverage_specificity-1.0.3.dist-info/METADATA
coverage_specificity-1.0.3.dist-info/WHEEL
coverage_specificity-1.0.3.dist-info/top_level.txt
coverage_specificity-1.0.3.dist-info/RECORD
