Metadata-Version: 2.1
Name: coverage-specificity
Version: 1.0.3
Summary: Python utility to calculate and vizualize coverage and specificity
Home-page: https://github.com/goxan/coverage-specificity
Author: Yaroslav Plaksin
Author-email: y.plaksin@innopolis.university
License: UNKNOWN
Platform: UNKNOWN
Requires-Dist: validclust
